{"note":"Don't delete this file! It's used internally to help with page regeneration.","google":"","name":"Twoffein-client","tagline":"Client for twoffein.de API","body":"# Twoffein-Client\r\nClient-Version: 0.1.0 | API-Version: 0.2\r\n\r\nThis client for [Twoffein](http://twoffein.com/)'s [API](http://twoffein.com/api-faq/).\r\n\r\n## Installation\r\n\r\nAdd this line to your application's Gemfile:\r\n\r\n    gem 'twoffein-client'\r\n\r\nAnd then execute:\r\n\r\n    $ bundle\r\n\r\nOr install it yourself as:\r\n\r\n    $ gem install twoffein-client\r\n\r\n## Usage\r\n\r\n```\r\nNAME\r\n    twoffein-client - Client for API 0.2 twoffein.de\r\n\r\nSYNOPSIS\r\n    twoffein-client [global options] command [command options] [arguments...]\r\n\r\nVERSION\r\n    0.1.0\r\n\r\nGLOBAL OPTIONS\r\n    --help    - Show this message\r\n    --version - Show version\r\n\r\nCOMMANDS\r\n    cookie  - Give cookie to RECEIVER\r\n    drinks  - List all drinks\r\n    help    - Shows a list of commands or help for one command\r\n    profile - List the profile, which you have chosen by PROFILE\r\n    tweet   - Tweet your drinking DRINK\r\n\r\n```\r\n\r\n### Credentials\r\n\r\nYou need your credentials (screen_name, api_key) to get access to the Twoffein-API. Please set these as\r\nshell environment variables `TWOFFEIN_SCREEN_NAME` and `TWOFFEIN_API_KEY`. Thank's!\r\n\r\n    TWOFFEIN_SCREEN_NAME=NAME TWOFFEIN_API_KEY=KEY twoffein-client drinks\r\n\r\n## Examples\r\n\r\n\r\n### Drinks\r\n\r\n**Input:**\r\n\r\n    twoffein-client drinks\r\n\r\n**Output:**\r\n```\r\nDrink                  (key)\r\n--------------------------------------------\r\nKaffee                 (kaffee)\r\nMilchkaffee            (milchkaffee)\r\nEiskaffee              (eiskaffee)\r\nEnergy Drink           (energiedrink)\r\nCola                   (cola)\r\nCola Light             (colalight)\r\nCola Zero              (colazero)\r\nCola-Mix               (colamix)\r\nCola-Mix Light         (colamixlight)\r\nCola-Mix Zero          (colamixzero)\r\nBubble Tea             (bubbletea)\r\nCherry Cola            (cherrycola)\r\nVanilla Cola           (vanillacola)\r\nCaffé Latte            (cafelatte)\r\nCaffé au Lait          (cafeaulait)\r\nLatte Macchiato        (lattemacchiato)\r\nEspresso Macciato      (espressomacciato)\r\nEspresso con Panne     (espressoconpanne)\r\nFlat White             (flatwhite)\r\nCaffé Breve            (caffebreve)\r\nCaffé Mocha            (caffemocha)\r\nAmericano              (americano)\r\nMelange                (melange)\r\nRed Eye                (redeye)\r\nTee                    (tee)\r\nEistee                 (eistee)\r\nKakao                  (kakao)\r\nMate                   (mate)\r\nEspresso               (espresso)\r\nCappuccino             (cappuccino)\r\nVannillochino          (vannillochino)\r\nInstantkaffee          (instantkaffee)\r\nMokka                  (mokka)\r\nChai-Latte             (chailatte)\r\nGrünen Tee             (guenertee)\r\nSchwarztee             (schwarztee)\r\n1337MATE               (leetmate)\r\nClub-Mate              (clubmate)\r\nClub-Mate Cola         (clubmatecola)\r\nICE-Tea KRAFTSTOFF     (kraftstoff)\r\nPremium-Cola           (premiumcola)\r\nDr Pepper              (drpepper)\r\nVita Cola              (vitacola)\r\nVita Cola Mix          (vitacolamix)\r\nVita Cola Pur          (vitacolapur)\r\nSchokocino             (schokocino)\r\nafri cola              (africola)\r\nafri sugarfree         (afrisugarfree)\r\nafri power             (afripower)\r\nfritz-kola             (fritzkola)\r\nfritz-kola stevia      (fritzkolastevia)\r\nfritz-kola zuckerfrei  (fritzkolazuckerfrei)\r\nmischmasch             (mischmasch)\r\nHaji Cola              (hajicola)\r\nKILLERFISH Hot Energy  (killerfishhotenergy)\r\nCafé Frappé            (cafefrappe)\r\nEnergy Shot            (energyshot)\r\nWasser                 (wasser)\r\nMineralwasser          (mineralwasser)\r\nApfelsaft              (apfelsaft)\r\nOrangensaft            (orangensaft)\r\nMilch                  (milch)\r\nSojamilch              (sojamilch)\r\nOrangenlimonade        (orangenlimonade)\r\nZitronenlimonade       (zitronenlimonade)\r\nKräuterlimonade        (kraeuterlimonade)\r\nApfelsaftschorle       (apfelsaftschorle)\r\nGinger Ale             (gingerale)\r\nTonic Water            (tonicwater)\r\nBitter Lemon           (bitterlemon)\r\nBananensaft            (bananensaft)\r\nTraubensaft            (traubensaft)\r\nMilchshake             (milchshake)\r\nJoghurtdrink           (joghurtdrink)\r\nSmoothie               (smoothie)\r\nEspresso Doppio        (espressodoppio)\r\nFassbrause             (fassbrause)\r\nAyran                  (ayran)\r\nFlora Power            (florapower)\r\nVOLT Cola              (voltcola)\r\nCOFAIN 699             (cofain669)\r\nErdbeersaft            (erdbeersaft)\r\nKiBa                   (kiba)\r\nMüllermilch            (muellermilch)\r\nMalzbier               (malzbier)\r\nRhabarberschorle       (rhabarberschorle)\r\n```\r\n\r\n### Drinks (filtered)\r\n\r\n**Input:**\r\n\r\n    twoffein-client drinks --grep club\r\n\r\n**Output:**\r\n```\r\nDrink           (key)\r\n------------------------------\r\nClub-Mate       (clubmate)\r\nClub-Mate Cola  (clubmatecola)\r\n```\r\n\r\n### Profile\r\n\r\n**Input:**\r\n\r\n    twoffein-client profile\r\n\r\n**Output:**\r\n```\r\nQuest:                     Blitzlicht\r\nDrink:                     Club-Mate\r\nRank:                      74\r\nRank Title:                Kaffeekännchen\r\nDrunken:                   16\r\nBluttwoffeinkonzentration: 1%\r\nFirst Login:               2012-07-08 13:36\r\nScreen Name:               DSIW\r\n```\r\n\r\n### Cookie\r\n\r\n**Input:**\r\n\r\n    twoffein-client cookie DSIW\r\n\r\n**Output:**\r\n```\r\nLol.\r\n```\r\n\r\n_Notice: You can't send yourself a cookie._\r\n\r\n### Tweet\r\n\r\n**Input:**\r\n\r\n    twoffein-client tweet clubmate\r\n\r\n**Output:**\r\n```\r\nIch trinke gerade Club-Mate.\r\nInfo: Youre Tweet has been tweeted. Thanks.\r\nDrinks today: 2\r\n```\r\n\r\n## Contributing\r\n\r\n1. Fork it\r\n2. Create your feature branch (`git checkout -b my-new-feature`)\r\n3. Commit your changes (`git commit -am 'Added some feature'`)\r\n4. Push to the branch (`git push origin my-new-feature`)\r\n5. Create new Pull Request\r\n"}